webfolder/__init__.py
webfolder-0.1.0.dist-info/LICENSE
webfolder-0.1.0.dist-info/METADATA
webfolder-0.1.0.dist-info/WHEEL
webfolder-0.1.0.dist-info/top_level.txt
webfolder-0.1.0.dist-info/RECORD
